{
  "biome_tiles": {
    "sheet_id": 1002,
    "tiles": [
      "000000000000000000000000000000",
      "000000000000000000000000000000",
      "066666666660000000000000000000",
      "066666666660000000000000000000",
      "066666666660000000000000000000",
      "066666666660000000000000000000",
      "066666666660000000000000000000",
      "066666666660000000000000000000",
      "000000000000000000000000000000"
    ]
  },
  "construction_tiles": {
    "sheet_id": 1003,
    "tiles": [
      "OOOOOOOOOOO0000000000000000000",
      "OOOOOOOOOOO0000000000000000000",
      "O00000000000000000000000000000",
      "O00000000000000000000000000000",
      "O00000000000000000000000000000",
      "O00000000000000000000000000000",
      "O00000000000000000000000000000",
      "O00000000000000000000000000000",
      "OOOOOOOOOOO0000000000000000000"
    ]
  },
  "cutscenes": [],
  "entities": [
    {
      "after_dialogue": "Nothing",
      "contents": null,
      "demands_attention": false,
      "destination": null,
      "dialogues": [],
      "direction": "Down",
      "display_conditions": [],
      "frame": {
        "h": 2,
        "w": 1,
        "x": 8,
        "y": 1
      },
      "id": 10909127,
      "is_consumable": false,
      "lock_type": "None",
      "species_id": 1011
    },
    {
      "after_dialogue": "Nothing",
      "contents": null,
      "demands_attention": false,
      "destination": {
        "direction": "None",
        "world": 10909115,
        "x": 0,
        "y": 0
      },
      "dialogues": [],
      "direction": "Down",
      "display_conditions": [],
      "frame": {
        "h": 1,
        "w": 1,
        "x": 8,
        "y": 2
      },
      "id": 10909128,
      "is_consumable": false,
      "lock_type": "None",
      "species_id": 1019
    },
    {
      "after_dialogue": "Nothing",
      "contents": null,
      "demands_attention": false,
      "destination": null,
      "dialogues": [],
      "direction": "Down",
      "display_conditions": [],
      "frame": {
        "h": 1,
        "w": 1,
        "x": 5,
        "y": 2
      },
      "id": 11962741,
      "is_consumable": false,
      "lock_type": "None",
      "species_id": 1090
    },
    {
      "after_dialogue": "Nothing",
      "contents": null,
      "demands_attention": false,
      "destination": null,
      "dialogues": [],
      "direction": "Down",
      "display_conditions": [],
      "frame": {
        "h": 1,
        "w": 1,
        "x": 5,
        "y": 6
      },
      "id": 11962746,
      "is_consumable": false,
      "lock_type": "None",
      "species_id": 1090
    },
    {
      "after_dialogue": "Nothing",
      "contents": null,
      "demands_attention": false,
      "destination": null,
      "dialogues": [],
      "direction": "Down",
      "display_conditions": [],
      "frame": {
        "h": 2,
        "w": 1,
        "x": 10,
        "y": 6
      },
      "id": 11962739,
      "is_consumable": false,
      "lock_type": "None",
      "species_id": 1017
    },
    {
      "after_dialogue": "Nothing",
      "contents": null,
      "demands_attention": false,
      "destination": null,
      "dialogues": [],
      "direction": "Down",
      "display_conditions": [],
      "frame": {
        "h": 2,
        "w": 1,
        "x": 10,
        "y": 2
      },
      "id": 11962738,
      "is_consumable": false,
      "lock_type": "None",
      "species_id": 1017
    },
    {
      "after_dialogue": "Nothing",
      "contents": null,
      "demands_attention": false,
      "destination": null,
      "dialogues": [],
      "direction": "Down",
      "display_conditions": [],
      "frame": {
        "h": 1,
        "w": 1,
        "x": 9,
        "y": 6
      },
      "id": 11962743,
      "is_consumable": false,
      "lock_type": "None",
      "species_id": 1090
    },
    {
      "after_dialogue": "Nothing",
      "contents": null,
      "demands_attention": false,
      "destination": null,
      "dialogues": [],
      "direction": "Down",
      "display_conditions": [],
      "frame": {
        "h": 1,
        "w": 1,
        "x": 9,
        "y": 2
      },
      "id": 11962742,
      "is_consumable": false,
      "lock_type": "None",
      "species_id": 1090
    },
    {
      "after_dialogue": "Nothing",
      "contents": null,
      "demands_attention": false,
      "destination": null,
      "dialogues": [],
      "direction": "Down",
      "display_conditions": [],
      "frame": {
        "h": 2,
        "w": 1,
        "x": 2,
        "y": 2
      },
      "id": 11962734,
      "is_consumable": false,
      "lock_type": "None",
      "species_id": 1017
    },
    {
      "after_dialogue": "Nothing",
      "contents": null,
      "demands_attention": false,
      "destination": null,
      "dialogues": [],
      "direction": "Down",
      "display_conditions": [],
      "frame": {
        "h": 2,
        "w": 1,
        "x": 2,
        "y": 6
      },
      "id": 11962735,
      "is_consumable": false,
      "lock_type": "None",
      "species_id": 1017
    },
    {
      "after_dialogue": "Nothing",
      "contents": null,
      "demands_attention": false,
      "destination": null,
      "dialogues": [],
      "direction": "Down",
      "display_conditions": [],
      "frame": {
        "h": 2,
        "w": 1,
        "x": 4,
        "y": 2
      },
      "id": 11962736,
      "is_consumable": false,
      "lock_type": "None",
      "species_id": 1017
    },
    {
      "after_dialogue": "Nothing",
      "contents": null,
      "demands_attention": false,
      "destination": null,
      "dialogues": [],
      "direction": "Down",
      "display_conditions": [],
      "frame": {
        "h": 2,
        "w": 1,
        "x": 4,
        "y": 6
      },
      "id": 11962737,
      "is_consumable": false,
      "lock_type": "None",
      "species_id": 1017
    },
    {
      "after_dialogue": "Nothing",
      "contents": null,
      "demands_attention": false,
      "destination": null,
      "dialogues": [],
      "direction": "Down",
      "display_conditions": [],
      "frame": {
        "h": 1,
        "w": 1,
        "x": 1,
        "y": 2
      },
      "id": 11962744,
      "is_consumable": false,
      "lock_type": "None",
      "species_id": 1090
    },
    {
      "after_dialogue": "Nothing",
      "contents": null,
      "demands_attention": false,
      "destination": null,
      "dialogues": [],
      "direction": "Down",
      "display_conditions": [],
      "frame": {
        "h": 1,
        "w": 1,
        "x": 1,
        "y": 6
      },
      "id": 11962745,
      "is_consumable": false,
      "lock_type": "None",
      "species_id": 1090
    },
    {
      "after_dialogue": "Nothing",
      "contents": null,
      "demands_attention": false,
      "destination": null,
      "dialogues": [],
      "direction": "Down",
      "display_conditions": [],
      "frame": {
        "h": 1,
        "w": 1,
        "x": 3,
        "y": 2
      },
      "id": 11962747,
      "is_consumable": false,
      "lock_type": "None",
      "species_id": 1012
    },
    {
      "after_dialogue": "Nothing",
      "contents": null,
      "demands_attention": false,
      "destination": null,
      "dialogues": [],
      "direction": "Down",
      "display_conditions": [],
      "frame": {
        "h": 1,
        "w": 1,
        "x": 3,
        "y": 3
      },
      "id": 11962748,
      "is_consumable": false,
      "lock_type": "None",
      "species_id": 1012
    },
    {
      "after_dialogue": "Nothing",
      "contents": null,
      "demands_attention": false,
      "destination": null,
      "dialogues": [],
      "direction": "Down",
      "display_conditions": [],
      "frame": {
        "h": 1,
        "w": 1,
        "x": 3,
        "y": 6
      },
      "id": 11962749,
      "is_consumable": false,
      "lock_type": "None",
      "species_id": 1012
    },
    {
      "after_dialogue": "Nothing",
      "contents": null,
      "demands_attention": false,
      "destination": null,
      "dialogues": [],
      "direction": "Down",
      "display_conditions": [],
      "frame": {
        "h": 1,
        "w": 1,
        "x": 3,
        "y": 7
      },
      "id": 11962750,
      "is_consumable": false,
      "lock_type": "None",
      "species_id": 1012
    },
    {
      "after_dialogue": "Nothing",
      "contents": null,
      "demands_attention": false,
      "destination": null,
      "dialogues": [],
      "direction": "Down",
      "display_conditions": [],
      "frame": {
        "h": 1,
        "w": 1,
        "x": 6,
        "y": 4
      },
      "id": 11962754,
      "is_consumable": false,
      "lock_type": "None",
      "species_id": 7000
    },
    {
      "after_dialogue": "Nothing",
      "contents": null,
      "demands_attention": false,
      "destination": null,
      "dialogues": [],
      "direction": "Down",
      "display_conditions": [],
      "frame": {
        "h": 2,
        "w": 1,
        "x": 4,
        "y": 4
      },
      "id": 11962755,
      "is_consumable": false,
      "lock_type": "None",
      "movement_directions": "FindHero",
      "species_id": 4004
    }
  ],
  "ephemeral_state": false,
  "id": 10909116,
  "light_conditions": "Day",
  "revision": 0,
  "world_type": "HouseInterior"
}