{
  "biome_tiles": {
    "sheet_id": 1002,
    "tiles": [
      "000000000000000000000000000000",
      "000000000000000000000000000000",
      "066666666660000000000000000000",
      "066666666660000000000000000000",
      "066666666660000000000000000000",
      "066666666660000000000000000000",
      "066666666660000000000000000000",
      "066666666660000000000000000000",
      "000000000000000000000000000000",
      "000000000000000000000000000000",
      "000000000000000000000000000000",
      "000000000000000000000000000000",
      "000000000000000000000000000000",
      "000000000000000000000000000000",
      "000000000000000000000000000000",
      "000000000000000000000000000000",
      "000000000000000000000000000000",
      "000000000000000000000000000000",
      "000000000000000000000000000000",
      "000000000000000000000000000000",
      "000000000000000000000000000000",
      "000000000000000000000000000000",
      "000000000000000000000000000000",
      "000000000000000000000000000000",
      "000000000000000000000000000000",
      "000000000000000000000000000000",
      "000000000000000000000000000000",
      "000000000000000000000000000000",
      "000000000000000000000000000000",
      "000000000000000000000000000000"
    ]
  },
  "construction_tiles": {
    "sheet_id": 1003,
    "tiles": [
      "444444444440000000000000000000",
      "444444444440000000000000000000",
      "4TTTTTTTTTT0000000000000000000",
      "4TTTTTTTTTT0000000000000000000",
      "4TTTTTTTTTT0000000000000000000",
      "4TTTTTTTTTT0000000000000000000",
      "4TTTTTTTTTT0000000000000000000",
      "4TTTTTTTTTT0000000000000000000",
      "444440044440000000000000000000",
      "000000000000000000000000000000",
      "000000000000000000000000000000",
      "000000000000000000000000000000",
      "000000000000000000000000000000",
      "000000000000000000000000000000",
      "000000000000000000000000000000",
      "000000000000000000000000000000",
      "000000000000000000000000000000",
      "000000000000000000000000000000",
      "000000000000000000000000000000",
      "000000000000000000000000000000",
      "000000000000000000000000000000",
      "000000000000000000000000000000",
      "000000000000000000000000000000",
      "000000000000000000000000000000",
      "000000000000000000000000000000",
      "000000000000000000000000000000",
      "000000000000000000000000000000",
      "000000000000000000000000000000",
      "000000000000000000000000000000",
      "000000000000000000000000000000"
    ]
  },
  "cutscenes": [],
  "entities": [
    {
      "after_dialogue": "Nothing",
      "contents": null,
      "demands_attention": false,
      "destination": {
        "direction": "None",
        "world": 1020,
        "x": 0,
        "y": 0
      },
      "dialogues": [],
      "direction": "Down",
      "display_conditions": [],
      "frame": {
        "h": 1,
        "w": 1,
        "x": 5,
        "y": 8
      },
      "id": 12745781,
      "is_consumable": false,
      "lock_type": "None",
      "species_id": 1019
    },
    {
      "after_dialogue": "Nothing",
      "contents": null,
      "demands_attention": false,
      "destination": {
        "direction": "None",
        "world": 1020,
        "x": 0,
        "y": 0
      },
      "dialogues": [],
      "direction": "Down",
      "display_conditions": [],
      "frame": {
        "h": 1,
        "w": 1,
        "x": 6,
        "y": 8
      },
      "id": 12745782,
      "is_consumable": false,
      "lock_type": "None",
      "species_id": 1019
    },
    {
      "after_dialogue": "Nothing",
      "contents": null,
      "demands_attention": false,
      "destination": null,
      "dialogues": [],
      "direction": "Down",
      "display_conditions": [],
      "frame": {
        "h": 2,
        "w": 1,
        "x": 1,
        "y": 1
      },
      "id": 13011661,
      "is_consumable": false,
      "lock_type": "None",
      "species_id": 1039
    },
    {
      "after_dialogue": "Nothing",
      "contents": null,
      "demands_attention": false,
      "destination": null,
      "dialogues": [],
      "direction": "Down",
      "display_conditions": [],
      "frame": {
        "h": 2,
        "w": 1,
        "x": 2,
        "y": 1
      },
      "id": 13011662,
      "is_consumable": false,
      "lock_type": "None",
      "species_id": 1039
    },
    {
      "after_dialogue": "Nothing",
      "contents": null,
      "demands_attention": false,
      "destination": null,
      "dialogues": [],
      "direction": "Down",
      "display_conditions": [],
      "frame": {
        "h": 2,
        "w": 1,
        "x": 3,
        "y": 1
      },
      "id": 13011663,
      "is_consumable": false,
      "lock_type": "None",
      "species_id": 1039
    },
    {
      "after_dialogue": "Nothing",
      "contents": null,
      "demands_attention": false,
      "destination": null,
      "dialogues": [],
      "direction": "Down",
      "display_conditions": [],
      "frame": {
        "h": 2,
        "w": 1,
        "x": 4,
        "y": 1
      },
      "id": 13011664,
      "is_consumable": false,
      "lock_type": "None",
      "species_id": 1039
    },
    {
      "after_dialogue": "Nothing",
      "contents": null,
      "demands_attention": false,
      "destination": null,
      "dialogues": [],
      "direction": "Down",
      "display_conditions": [],
      "frame": {
        "h": 2,
        "w": 1,
        "x": 5,
        "y": 1
      },
      "id": 13011665,
      "is_consumable": false,
      "lock_type": "None",
      "species_id": 1039
    },
    {
      "after_dialogue": "Nothing",
      "contents": null,
      "demands_attention": false,
      "destination": null,
      "dialogues": [],
      "direction": "Down",
      "display_conditions": [],
      "frame": {
        "h": 2,
        "w": 1,
        "x": 6,
        "y": 1
      },
      "id": 13011666,
      "is_consumable": false,
      "lock_type": "None",
      "species_id": 1039
    },
    {
      "after_dialogue": "Nothing",
      "contents": null,
      "demands_attention": false,
      "destination": null,
      "dialogues": [],
      "direction": "Down",
      "display_conditions": [],
      "frame": {
        "h": 2,
        "w": 1,
        "x": 8,
        "y": 1
      },
      "id": 13011667,
      "is_consumable": false,
      "lock_type": "None",
      "species_id": 1039
    },
    {
      "after_dialogue": "Nothing",
      "contents": null,
      "demands_attention": false,
      "destination": null,
      "dialogues": [],
      "direction": "Down",
      "display_conditions": [],
      "frame": {
        "h": 2,
        "w": 1,
        "x": 7,
        "y": 1
      },
      "id": 13011668,
      "is_consumable": false,
      "lock_type": "None",
      "species_id": 1039
    },
    {
      "after_dialogue": "Nothing",
      "contents": null,
      "demands_attention": false,
      "destination": null,
      "dialogues": [],
      "direction": "Down",
      "display_conditions": [],
      "frame": {
        "h": 2,
        "w": 1,
        "x": 9,
        "y": 1
      },
      "id": 13011669,
      "is_consumable": false,
      "lock_type": "None",
      "species_id": 1039
    },
    {
      "after_dialogue": "Nothing",
      "contents": null,
      "demands_attention": false,
      "destination": null,
      "dialogues": [],
      "direction": "Down",
      "display_conditions": [],
      "frame": {
        "h": 2,
        "w": 1,
        "x": 10,
        "y": 1
      },
      "id": 13011670,
      "is_consumable": false,
      "lock_type": "None",
      "species_id": 1039
    },
    {
      "after_dialogue": "Nothing",
      "contents": null,
      "demands_attention": false,
      "destination": null,
      "dialogues": [],
      "direction": "Down",
      "display_conditions": [],
      "frame": {
        "h": 2,
        "w": 1,
        "x": 1,
        "y": 2
      },
      "id": 13011671,
      "is_consumable": false,
      "lock_type": "None",
      "species_id": 1039
    },
    {
      "after_dialogue": "Nothing",
      "contents": null,
      "demands_attention": false,
      "destination": null,
      "dialogues": [],
      "direction": "Down",
      "display_conditions": [],
      "frame": {
        "h": 2,
        "w": 1,
        "x": 2,
        "y": 2
      },
      "id": 13011672,
      "is_consumable": false,
      "lock_type": "None",
      "species_id": 1039
    },
    {
      "after_dialogue": "Nothing",
      "contents": null,
      "demands_attention": false,
      "destination": null,
      "dialogues": [],
      "direction": "Down",
      "display_conditions": [],
      "frame": {
        "h": 2,
        "w": 1,
        "x": 3,
        "y": 2
      },
      "id": 13011673,
      "is_consumable": false,
      "lock_type": "None",
      "species_id": 1039
    },
    {
      "after_dialogue": "Nothing",
      "contents": null,
      "demands_attention": false,
      "destination": null,
      "dialogues": [],
      "direction": "Down",
      "display_conditions": [],
      "frame": {
        "h": 2,
        "w": 1,
        "x": 4,
        "y": 2
      },
      "id": 13011674,
      "is_consumable": false,
      "lock_type": "None",
      "species_id": 1039
    },
    {
      "after_dialogue": "Nothing",
      "contents": null,
      "demands_attention": false,
      "destination": null,
      "dialogues": [],
      "direction": "Down",
      "display_conditions": [],
      "frame": {
        "h": 2,
        "w": 1,
        "x": 5,
        "y": 2
      },
      "id": 13011675,
      "is_consumable": false,
      "lock_type": "None",
      "species_id": 1039
    },
    {
      "after_dialogue": "Nothing",
      "contents": null,
      "demands_attention": false,
      "destination": null,
      "dialogues": [],
      "direction": "Down",
      "display_conditions": [],
      "frame": {
        "h": 2,
        "w": 1,
        "x": 6,
        "y": 2
      },
      "id": 13011676,
      "is_consumable": false,
      "lock_type": "None",
      "species_id": 1039
    },
    {
      "after_dialogue": "Nothing",
      "contents": null,
      "demands_attention": false,
      "destination": null,
      "dialogues": [],
      "direction": "Down",
      "display_conditions": [],
      "frame": {
        "h": 2,
        "w": 1,
        "x": 7,
        "y": 2
      },
      "id": 13011677,
      "is_consumable": false,
      "lock_type": "None",
      "species_id": 1039
    },
    {
      "after_dialogue": "Nothing",
      "contents": null,
      "demands_attention": false,
      "destination": null,
      "dialogues": [],
      "direction": "Down",
      "display_conditions": [],
      "frame": {
        "h": 2,
        "w": 1,
        "x": 8,
        "y": 2
      },
      "id": 13011678,
      "is_consumable": false,
      "lock_type": "None",
      "species_id": 1039
    },
    {
      "after_dialogue": "Nothing",
      "contents": null,
      "demands_attention": false,
      "destination": null,
      "dialogues": [],
      "direction": "Down",
      "display_conditions": [],
      "frame": {
        "h": 2,
        "w": 1,
        "x": 1,
        "y": 3
      },
      "id": 13011679,
      "is_consumable": false,
      "lock_type": "None",
      "species_id": 1039
    },
    {
      "after_dialogue": "Nothing",
      "contents": null,
      "demands_attention": false,
      "destination": null,
      "dialogues": [],
      "direction": "Down",
      "display_conditions": [],
      "frame": {
        "h": 2,
        "w": 1,
        "x": 1,
        "y": 4
      },
      "id": 13011680,
      "is_consumable": false,
      "lock_type": "None",
      "species_id": 1039
    },
    {
      "after_dialogue": "Nothing",
      "contents": null,
      "demands_attention": false,
      "destination": null,
      "dialogues": [],
      "direction": "Down",
      "display_conditions": [],
      "frame": {
        "h": 2,
        "w": 1,
        "x": 1,
        "y": 5
      },
      "id": 13011681,
      "is_consumable": false,
      "lock_type": "None",
      "species_id": 1039
    },
    {
      "after_dialogue": "Nothing",
      "contents": null,
      "demands_attention": false,
      "destination": null,
      "dialogues": [],
      "direction": "Down",
      "display_conditions": [],
      "frame": {
        "h": 2,
        "w": 1,
        "x": 2,
        "y": 3
      },
      "id": 13011682,
      "is_consumable": false,
      "lock_type": "None",
      "species_id": 1039
    },
    {
      "after_dialogue": "Nothing",
      "contents": null,
      "demands_attention": false,
      "destination": null,
      "dialogues": [],
      "direction": "Down",
      "display_conditions": [],
      "frame": {
        "h": 2,
        "w": 1,
        "x": 9,
        "y": 2
      },
      "id": 13011683,
      "is_consumable": false,
      "lock_type": "None",
      "species_id": 1038
    },
    {
      "after_dialogue": "Nothing",
      "contents": null,
      "demands_attention": false,
      "destination": null,
      "dialogues": [],
      "direction": "Down",
      "display_conditions": [],
      "frame": {
        "h": 2,
        "w": 1,
        "x": 10,
        "y": 2
      },
      "id": 13011684,
      "is_consumable": false,
      "lock_type": "None",
      "species_id": 1038
    },
    {
      "after_dialogue": "Nothing",
      "contents": null,
      "demands_attention": false,
      "destination": null,
      "dialogues": [],
      "direction": "Down",
      "display_conditions": [],
      "frame": {
        "h": 2,
        "w": 1,
        "x": 10,
        "y": 3
      },
      "id": 13011685,
      "is_consumable": false,
      "lock_type": "None",
      "species_id": 1038
    },
    {
      "after_dialogue": "Nothing",
      "contents": null,
      "demands_attention": false,
      "destination": null,
      "dialogues": [],
      "direction": "Down",
      "display_conditions": [],
      "frame": {
        "h": 2,
        "w": 1,
        "x": 9,
        "y": 3
      },
      "id": 13011686,
      "is_consumable": false,
      "lock_type": "None",
      "species_id": 1038
    },
    {
      "after_dialogue": "Nothing",
      "contents": null,
      "demands_attention": false,
      "destination": null,
      "dialogues": [],
      "direction": "Down",
      "display_conditions": [],
      "frame": {
        "h": 2,
        "w": 1,
        "x": 8,
        "y": 3
      },
      "id": 13011687,
      "is_consumable": false,
      "lock_type": "None",
      "species_id": 1038
    },
    {
      "after_dialogue": "Nothing",
      "contents": null,
      "demands_attention": false,
      "destination": null,
      "dialogues": [],
      "direction": "Down",
      "display_conditions": [],
      "frame": {
        "h": 2,
        "w": 1,
        "x": 7,
        "y": 3
      },
      "id": 13011688,
      "is_consumable": false,
      "lock_type": "None",
      "species_id": 1038
    },
    {
      "after_dialogue": "Nothing",
      "contents": null,
      "demands_attention": false,
      "destination": null,
      "dialogues": [],
      "direction": "Down",
      "display_conditions": [],
      "frame": {
        "h": 2,
        "w": 1,
        "x": 6,
        "y": 3
      },
      "id": 13011689,
      "is_consumable": false,
      "lock_type": "None",
      "species_id": 1038
    },
    {
      "after_dialogue": "Nothing",
      "contents": null,
      "demands_attention": false,
      "destination": null,
      "dialogues": [],
      "direction": "Down",
      "display_conditions": [],
      "frame": {
        "h": 2,
        "w": 1,
        "x": 5,
        "y": 3
      },
      "id": 13011690,
      "is_consumable": false,
      "lock_type": "None",
      "species_id": 1038
    },
    {
      "after_dialogue": "Nothing",
      "contents": null,
      "demands_attention": false,
      "destination": null,
      "dialogues": [],
      "direction": "Down",
      "display_conditions": [],
      "frame": {
        "h": 2,
        "w": 1,
        "x": 4,
        "y": 3
      },
      "id": 13011691,
      "is_consumable": false,
      "lock_type": "None",
      "species_id": 1038
    },
    {
      "after_dialogue": "Nothing",
      "contents": null,
      "demands_attention": false,
      "destination": null,
      "dialogues": [],
      "direction": "Down",
      "display_conditions": [],
      "frame": {
        "h": 2,
        "w": 1,
        "x": 3,
        "y": 3
      },
      "id": 13011692,
      "is_consumable": false,
      "lock_type": "None",
      "species_id": 1038
    },
    {
      "after_dialogue": "Nothing",
      "contents": null,
      "demands_attention": false,
      "destination": null,
      "dialogues": [],
      "direction": "Down",
      "display_conditions": [],
      "frame": {
        "h": 2,
        "w": 1,
        "x": 2,
        "y": 4
      },
      "id": 13011693,
      "is_consumable": false,
      "lock_type": "None",
      "species_id": 1038
    },
    {
      "after_dialogue": "Nothing",
      "contents": null,
      "demands_attention": false,
      "destination": null,
      "dialogues": [],
      "direction": "Down",
      "display_conditions": [],
      "frame": {
        "h": 2,
        "w": 1,
        "x": 3,
        "y": 4
      },
      "id": 13011694,
      "is_consumable": false,
      "lock_type": "None",
      "species_id": 1038
    },
    {
      "after_dialogue": "Nothing",
      "contents": null,
      "demands_attention": false,
      "destination": null,
      "dialogues": [],
      "direction": "Down",
      "display_conditions": [],
      "frame": {
        "h": 2,
        "w": 1,
        "x": 4,
        "y": 4
      },
      "id": 13011695,
      "is_consumable": false,
      "lock_type": "None",
      "species_id": 1038
    },
    {
      "after_dialogue": "Nothing",
      "contents": null,
      "demands_attention": false,
      "destination": null,
      "dialogues": [],
      "direction": "Down",
      "display_conditions": [],
      "frame": {
        "h": 2,
        "w": 1,
        "x": 5,
        "y": 4
      },
      "id": 13011696,
      "is_consumable": false,
      "lock_type": "None",
      "species_id": 1038
    },
    {
      "after_dialogue": "Nothing",
      "contents": null,
      "demands_attention": false,
      "destination": null,
      "dialogues": [],
      "direction": "Down",
      "display_conditions": [],
      "frame": {
        "h": 2,
        "w": 1,
        "x": 6,
        "y": 4
      },
      "id": 13011697,
      "is_consumable": false,
      "lock_type": "None",
      "species_id": 1038
    },
    {
      "after_dialogue": "Nothing",
      "contents": null,
      "demands_attention": false,
      "destination": null,
      "dialogues": [],
      "direction": "Down",
      "display_conditions": [],
      "frame": {
        "h": 2,
        "w": 1,
        "x": 7,
        "y": 4
      },
      "id": 13011698,
      "is_consumable": false,
      "lock_type": "None",
      "species_id": 1038
    },
    {
      "after_dialogue": "Nothing",
      "contents": null,
      "demands_attention": false,
      "destination": null,
      "dialogues": [],
      "direction": "Down",
      "display_conditions": [],
      "frame": {
        "h": 2,
        "w": 1,
        "x": 2,
        "y": 5
      },
      "id": 13011699,
      "is_consumable": false,
      "lock_type": "None",
      "species_id": 1038
    },
    {
      "after_dialogue": "Nothing",
      "contents": null,
      "demands_attention": false,
      "destination": null,
      "dialogues": [],
      "direction": "Down",
      "display_conditions": [],
      "frame": {
        "h": 2,
        "w": 1,
        "x": 10,
        "y": 4
      },
      "id": 13011700,
      "is_consumable": false,
      "lock_type": "None",
      "species_id": 1073
    },
    {
      "after_dialogue": "Nothing",
      "contents": null,
      "demands_attention": false,
      "destination": null,
      "dialogues": [],
      "direction": "Down",
      "display_conditions": [],
      "frame": {
        "h": 2,
        "w": 1,
        "x": 9,
        "y": 4
      },
      "id": 13011701,
      "is_consumable": false,
      "lock_type": "None",
      "species_id": 1073
    },
    {
      "after_dialogue": "Nothing",
      "contents": null,
      "demands_attention": false,
      "destination": null,
      "dialogues": [],
      "direction": "Down",
      "display_conditions": [],
      "frame": {
        "h": 2,
        "w": 1,
        "x": 8,
        "y": 4
      },
      "id": 13011702,
      "is_consumable": false,
      "lock_type": "None",
      "species_id": 1073
    },
    {
      "after_dialogue": "Nothing",
      "contents": null,
      "demands_attention": false,
      "destination": null,
      "dialogues": [],
      "direction": "Down",
      "display_conditions": [],
      "frame": {
        "h": 2,
        "w": 1,
        "x": 9,
        "y": 5
      },
      "id": 13011703,
      "is_consumable": false,
      "lock_type": "None",
      "species_id": 1073
    },
    {
      "after_dialogue": "Nothing",
      "contents": null,
      "demands_attention": false,
      "destination": null,
      "dialogues": [],
      "direction": "Down",
      "display_conditions": [],
      "frame": {
        "h": 2,
        "w": 1,
        "x": 10,
        "y": 5
      },
      "id": 13011704,
      "is_consumable": false,
      "lock_type": "None",
      "species_id": 1073
    },
    {
      "after_dialogue": "Nothing",
      "contents": null,
      "demands_attention": false,
      "destination": null,
      "dialogues": [],
      "direction": "Down",
      "display_conditions": [],
      "frame": {
        "h": 2,
        "w": 1,
        "x": 10,
        "y": 6
      },
      "id": 13011705,
      "is_consumable": false,
      "lock_type": "None",
      "species_id": 1073
    },
    {
      "after_dialogue": "Nothing",
      "contents": null,
      "demands_attention": false,
      "destination": null,
      "dialogues": [],
      "direction": "Down",
      "display_conditions": [],
      "frame": {
        "h": 2,
        "w": 1,
        "x": 9,
        "y": 6
      },
      "id": 13011706,
      "is_consumable": false,
      "lock_type": "None",
      "species_id": 1073
    },
    {
      "after_dialogue": "Nothing",
      "contents": null,
      "demands_attention": false,
      "destination": null,
      "dialogues": [],
      "direction": "Down",
      "display_conditions": [],
      "frame": {
        "h": 2,
        "w": 1,
        "x": 8,
        "y": 6
      },
      "id": 13011707,
      "is_consumable": false,
      "lock_type": "None",
      "species_id": 1073
    },
    {
      "after_dialogue": "Nothing",
      "contents": null,
      "demands_attention": false,
      "destination": null,
      "dialogues": [],
      "direction": "Down",
      "display_conditions": [],
      "frame": {
        "h": 2,
        "w": 1,
        "x": 8,
        "y": 5
      },
      "id": 13011708,
      "is_consumable": false,
      "lock_type": "None",
      "species_id": 1073
    },
    {
      "after_dialogue": "Nothing",
      "contents": null,
      "demands_attention": false,
      "destination": null,
      "dialogues": [],
      "direction": "Down",
      "display_conditions": [],
      "frame": {
        "h": 2,
        "w": 1,
        "x": 7,
        "y": 5
      },
      "id": 13011709,
      "is_consumable": false,
      "lock_type": "None",
      "species_id": 1073
    },
    {
      "after_dialogue": "Nothing",
      "contents": null,
      "demands_attention": false,
      "destination": null,
      "dialogues": [],
      "direction": "Down",
      "display_conditions": [],
      "frame": {
        "h": 2,
        "w": 1,
        "x": 2,
        "y": 6
      },
      "id": 13011710,
      "is_consumable": false,
      "lock_type": "None",
      "species_id": 1073
    },
    {
      "after_dialogue": "Nothing",
      "contents": null,
      "demands_attention": false,
      "destination": null,
      "dialogues": [],
      "direction": "Down",
      "display_conditions": [],
      "frame": {
        "h": 2,
        "w": 1,
        "x": 1,
        "y": 6
      },
      "id": 13011711,
      "is_consumable": false,
      "lock_type": "None",
      "species_id": 1073
    },
    {
      "after_dialogue": "Nothing",
      "contents": null,
      "demands_attention": false,
      "destination": null,
      "dialogues": [],
      "direction": "Down",
      "display_conditions": [],
      "frame": {
        "h": 2,
        "w": 1,
        "x": 3,
        "y": 5
      },
      "id": 13011712,
      "is_consumable": false,
      "lock_type": "None",
      "species_id": 1073
    },
    {
      "after_dialogue": "Nothing",
      "contents": null,
      "demands_attention": false,
      "destination": null,
      "dialogues": [],
      "direction": "Down",
      "display_conditions": [],
      "frame": {
        "h": 1,
        "w": 1,
        "x": 3,
        "y": 7
      },
      "id": 13011713,
      "is_consumable": false,
      "lock_type": "None",
      "species_id": 7000
    }
  ],
  "ephemeral_state": false,
  "id": 12745779,
  "light_conditions": "Day",
  "revision": 0,
  "soundtrack": null,
  "world_type": "HouseInterior"
}